core_infinity_stones/__init__.py
core_infinity_stones/auth/__init__.py
core_infinity_stones/auth/authenticator.py
core_infinity_stones/auth/config.py
core_infinity_stones/auth/constants.py
core_infinity_stones/auth/errors.py
core_infinity_stones/auth/http_auth.py
core_infinity_stones/auth/schemas.py
core_infinity_stones/core/__init__.py
core_infinity_stones/core/local_cache.py
core_infinity_stones/core/utils/__init__.py
core_infinity_stones/core/utils/decorators.py
core_infinity_stones/core/utils/helpers.py
core_infinity_stones/errors/__init__.py
core_infinity_stones/errors/base_error.py
core_infinity_stones/errors/map_missing_keys_error.py
core_infinity_stones/errors/response_status_code_error.py
core_infinity_stones/logging/__init__.py
core_infinity_stones/logging/logger.py
core_infinity_stones/logging/native_logger.py
core_infinity_stones/logging/schemas.py
core_infinity_stones/networking/__init__.py
core_infinity_stones/networking/httpx_client.py
core_infinity_stones/networking/response_handler.py
core_infinity_stones/networking/schemas.py
core_infinity_stones/redis_client/__init__.py
core_infinity_stones/redis_client/redis_client.py
core_infinity_stones/serialization/__init__.py
core_infinity_stones/serialization/base_model_response_decoder.py
core_infinity_stones/serialization/schemas.py
core_infinity_stones/serialization/xml_encoder.py
core_infinity_stones-0.1.20.dist-info/LICENSE
core_infinity_stones-0.1.20.dist-info/METADATA
core_infinity_stones-0.1.20.dist-info/WHEEL
core_infinity_stones-0.1.20.dist-info/top_level.txt
core_infinity_stones-0.1.20.dist-info/RECORD
