Metadata-Version: 2.2
Name: core_infinity_stones
Version: 0.1.20
Requires-Python: >=3.6
License-File: LICENSE
Requires-Dist: annotated-types==0.7.0
Requires-Dist: anyio==4.8.0
Requires-Dist: certifi==2024.12.14
Requires-Dist: h11==0.14.0
Requires-Dist: httpcore==1.0.8
Requires-Dist: httpx==0.28.1
Requires-Dist: idna==3.10
Requires-Dist: pydantic==2.10.6
Requires-Dist: pydantic_core==2.27.2
Requires-Dist: sniffio==1.3.1
Requires-Dist: typing_extensions==4.12.2
Dynamic: description
Dynamic: description-content-type
Dynamic: requires-dist
Dynamic: requires-python
